<?xml version="1.0"?>
<rdf:RDF
    xmlns:rdf="http://www.w3.org/1999/02/22-rdf-syntax-ns#"
    xmlns:j.0="http://vitro.mannlib.cornell.edu/ns/vitro/0.7#"
    xmlns:owl="http://www.w3.org/2002/07/owl#"
    xmlns:j.1="http://vivoweb.org/harvester/"
    xmlns:j.2="http://purl.org/ontology/bibo/"
    xmlns:rdfs="http://www.w3.org/2000/01/rdf-schema#"
    xmlns:j.3="http://vivoweb.org/ontology/core#"
    xmlns:j.4="http://xmlns.com/foaf/0.1/">
  <j.2:Document rdf:about="http://vivo.health.unm.edu/individual/n1840546625">
    <j.3:freetextKeyword>Avoidance Learning</j.3:freetextKeyword>
    <j.0:mostSpecificType rdf:resource="http://purl.org/ontology/bibo/AcademicArticle"/>
    <j.3:freetextKeyword>Adaptation, Psychological</j.3:freetextKeyword>
    <rdfs:label>Avoidant coping with health problems is related to poorer quality of life among lung transplant candidates.</rdfs:label>
    <j.2:number>3</j.2:number>
    <j.3:freetextKeyword>Male</j.3:freetextKeyword>
    <j.3:freetextKeyword>Female</j.3:freetextKeyword>
    <j.3:dateTimeValue>
      <j.3:DateTimeValue rdf:about="http://vivo.health.unm.edu/individual/n1854081671">
        <j.3:dateTime rdf:datatype="http://www.w3.org/2001/XMLSchema#dateTime"
        >2003-09-01T00:00:00</j.3:dateTime>
        <j.3:dateTimePrecision rdf:resource="http://vivoweb.org/ontology/core#yearMonthPrecision"/>
      </j.3:DateTimeValue>
    </j.3:dateTimeValue>
    <j.3:informationResourceInAuthorship>
      <j.3:DependentResource rdf:about="http://vivo.health.unm.edu/individual/n1652848169">
        <j.3:authorRank rdf:datatype="http://www.w3.org/2001/XMLSchema#integer"
        >5</j.3:authorRank>
        <j.3:linkedInformationResource rdf:resource="http://vivo.health.unm.edu/individual/n1840546625"/>
        <j.3:linkedAuthor>
          <j.1:excludeEntity rdf:about="http://vivo.health.unm.edu/individual/n1531922180">
            <j.3:middleName>L</j.3:middleName>
            <j.3:authorInAuthorship rdf:resource="http://vivo.health.unm.edu/individual/n1652848169"/>
            <j.4:firstName>Robert</j.4:firstName>
            <j.4:lastName>Kormos</j.4:lastName>
            <rdfs:label>Kormos, Robert L</rdfs:label>
            <rdf:type rdf:resource="http://xmlns.com/foaf/0.1/Person"/>
            <rdf:type rdf:resource="http://vitro.mannlib.cornell.edu/ns/vitro/0.7#Flag1Value1Thing"/>
          </j.1:excludeEntity>
        </j.3:linkedAuthor>
        <rdfs:label>Authorship for Kormos, Robert L</rdfs:label>
        <rdf:type rdf:resource="http://vitro.mannlib.cornell.edu/ns/vitro/0.7#DependentResource"/>
        <rdf:type rdf:resource="http://vivoweb.org/ontology/core#Authorship"/>
        <rdf:type rdf:resource="http://vitro.mannlib.cornell.edu/ns/vitro/0.7#Flag1Value1Thing"/>
      </j.3:DependentResource>
    </j.3:informationResourceInAuthorship>
    <j.3:freetextKeyword>Middle Aged</j.3:freetextKeyword>
    <rdf:type rdf:resource="http://purl.org/ontology/bibo/AcademicArticle"/>
    <j.3:informationResourceInAuthorship>
      <j.3:DependentResource rdf:about="http://vivo.health.unm.edu/individual/n1571855747">
        <j.3:authorRank rdf:datatype="http://www.w3.org/2001/XMLSchema#integer"
        >8</j.3:authorRank>
        <j.3:linkedInformationResource rdf:resource="http://vivo.health.unm.edu/individual/n1840546625"/>
        <j.3:linkedAuthor>
          <j.1:excludeEntity rdf:about="http://vivo.health.unm.edu/individual/n470061945">
            <j.3:middleName>D</j.3:middleName>
            <j.3:authorInAuthorship rdf:resource="http://vivo.health.unm.edu/individual/n1571855747"/>
            <j.4:firstName>Jan</j.4:firstName>
            <j.4:lastName>Manzetti</j.4:lastName>
            <rdfs:label>Manzetti, Jan D</rdfs:label>
            <rdf:type rdf:resource="http://xmlns.com/foaf/0.1/Person"/>
            <rdf:type rdf:resource="http://vitro.mannlib.cornell.edu/ns/vitro/0.7#Flag1Value1Thing"/>
          </j.1:excludeEntity>
        </j.3:linkedAuthor>
        <rdfs:label>Authorship for Manzetti, Jan D</rdfs:label>
        <rdf:type rdf:resource="http://vitro.mannlib.cornell.edu/ns/vitro/0.7#DependentResource"/>
        <rdf:type rdf:resource="http://vivoweb.org/ontology/core#Authorship"/>
        <rdf:type rdf:resource="http://vitro.mannlib.cornell.edu/ns/vitro/0.7#Flag1Value1Thing"/>
      </j.3:DependentResource>
    </j.3:informationResourceInAuthorship>
    <j.3:freetextKeyword>Socioeconomic Factors</j.3:freetextKeyword>
    <j.3:freetextKeyword>Activities of Daily Living</j.3:freetextKeyword>
    <j.3:Title>Avoidant coping with health problems is related to poorer quality of life among lung transplant candidates.</j.3:Title>
    <j.3:informationResourceInAuthorship>
      <j.3:DependentResource rdf:about="http://vivo.health.unm.edu/individual/n716436149">
        <j.3:authorRank rdf:datatype="http://www.w3.org/2001/XMLSchema#integer"
        >7</j.3:authorRank>
        <j.3:linkedInformationResource rdf:resource="http://vivo.health.unm.edu/individual/n1840546625"/>
        <j.3:linkedAuthor>
          <j.1:excludeEntity rdf:about="http://vivo.health.unm.edu/individual/n2079084606">
            <j.3:middleName>F</j.3:middleName>
            <j.3:authorInAuthorship rdf:resource="http://vivo.health.unm.edu/individual/n716436149"/>
            <j.4:firstName>Andrea</j.4:firstName>
            <j.4:lastName>DiMartini</j.4:lastName>
            <rdfs:label>DiMartini, Andrea F</rdfs:label>
            <rdf:type rdf:resource="http://xmlns.com/foaf/0.1/Person"/>
            <rdf:type rdf:resource="http://vitro.mannlib.cornell.edu/ns/vitro/0.7#Flag1Value1Thing"/>
          </j.1:excludeEntity>
        </j.3:linkedAuthor>
        <rdfs:label>Authorship for DiMartini, Andrea F</rdfs:label>
        <rdf:type rdf:resource="http://vitro.mannlib.cornell.edu/ns/vitro/0.7#DependentResource"/>
        <rdf:type rdf:resource="http://vivoweb.org/ontology/core#Authorship"/>
        <rdf:type rdf:resource="http://vitro.mannlib.cornell.edu/ns/vitro/0.7#Flag1Value1Thing"/>
      </j.3:DependentResource>
    </j.3:informationResourceInAuthorship>
    <j.3:freetextKeyword>Depression</j.3:freetextKeyword>
    <j.2:volume>13</j.2:volume>
    <j.3:freetextKeyword>Lung Transplantation</j.3:freetextKeyword>
    <j.3:informationResourceInAuthorship>
      <j.3:DependentResource rdf:about="http://vivo.health.unm.edu/individual/n1874079704">
        <j.3:authorRank rdf:datatype="http://www.w3.org/2001/XMLSchema#integer"
        >2</j.3:authorRank>
        <j.3:linkedInformationResource rdf:resource="http://vivo.health.unm.edu/individual/n1840546625"/>
        <j.3:linkedAuthor>
          <j.1:excludeEntity rdf:about="http://vivo.health.unm.edu/individual/n1890519896">
            <j.3:middleName>Amanda</j.3:middleName>
            <j.3:authorInAuthorship rdf:resource="http://vivo.health.unm.edu/individual/n1874079704"/>
            <j.4:firstName>Mary</j.4:firstName>
            <j.4:lastName>Dew</j.4:lastName>
            <rdfs:label>Dew, Mary Amanda</rdfs:label>
            <rdf:type rdf:resource="http://xmlns.com/foaf/0.1/Person"/>
            <rdf:type rdf:resource="http://vitro.mannlib.cornell.edu/ns/vitro/0.7#Flag1Value1Thing"/>
          </j.1:excludeEntity>
        </j.3:linkedAuthor>
        <rdfs:label>Authorship for Dew, Mary Amanda</rdfs:label>
        <rdf:type rdf:resource="http://vitro.mannlib.cornell.edu/ns/vitro/0.7#DependentResource"/>
        <rdf:type rdf:resource="http://vivoweb.org/ontology/core#Authorship"/>
        <rdf:type rdf:resource="http://vitro.mannlib.cornell.edu/ns/vitro/0.7#Flag1Value1Thing"/>
      </j.3:DependentResource>
    </j.3:informationResourceInAuthorship>
    <j.2:pmid>14558632</j.2:pmid>
    <j.3:freetextKeyword>Emotions</j.3:freetextKeyword>
    <j.3:informationResourceInAuthorship>
      <j.3:DependentResource rdf:about="http://vivo.health.unm.edu/individual/n1091132177">
        <j.3:authorRank rdf:datatype="http://www.w3.org/2001/XMLSchema#integer"
        >6</j.3:authorRank>
        <j.3:linkedInformationResource rdf:resource="http://vivo.health.unm.edu/individual/n1840546625"/>
        <j.3:linkedAuthor>
          <j.1:excludeEntity rdf:about="http://vivo.health.unm.edu/individual/n1427039563">
            <j.3:middleName>M</j.3:middleName>
            <j.3:authorInAuthorship rdf:resource="http://vivo.health.unm.edu/individual/n1091132177"/>
            <j.4:firstName>Jean</j.4:firstName>
            <j.4:lastName>Goycoolea</j.4:lastName>
            <rdfs:label>Goycoolea, Jean M</rdfs:label>
            <rdf:type rdf:resource="http://xmlns.com/foaf/0.1/Person"/>
            <rdf:type rdf:resource="http://vitro.mannlib.cornell.edu/ns/vitro/0.7#Flag1Value1Thing"/>
          </j.1:excludeEntity>
        </j.3:linkedAuthor>
        <rdfs:label>Authorship for Goycoolea, Jean M</rdfs:label>
        <rdf:type rdf:resource="http://vitro.mannlib.cornell.edu/ns/vitro/0.7#DependentResource"/>
        <rdf:type rdf:resource="http://vivoweb.org/ontology/core#Authorship"/>
        <rdf:type rdf:resource="http://vitro.mannlib.cornell.edu/ns/vitro/0.7#Flag1Value1Thing"/>
      </j.3:DependentResource>
    </j.3:informationResourceInAuthorship>
    <rdf:type rdf:resource="http://www.w3.org/2002/07/owl#Thing"/>
    <j.3:freetextKeyword>Social Support</j.3:freetextKeyword>
    <j.3:informationResourceInAuthorship>
      <j.3:DependentResource rdf:about="http://vivo.health.unm.edu/individual/n248967242">
        <j.3:authorRank rdf:datatype="http://www.w3.org/2001/XMLSchema#integer"
        >4</j.3:authorRank>
        <j.3:linkedInformationResource rdf:resource="http://vivo.health.unm.edu/individual/n1840546625"/>
        <j.3:linkedAuthor>
          <j.1:excludeEntity rdf:about="http://vivo.health.unm.edu/individual/n1577696326">
            <j.3:authorInAuthorship rdf:resource="http://vivo.health.unm.edu/individual/n248967242"/>
            <j.4:firstName>Martica</j.4:firstName>
            <j.4:lastName>Hall</j.4:lastName>
            <rdfs:label>Hall, Martica</rdfs:label>
            <rdf:type rdf:resource="http://xmlns.com/foaf/0.1/Person"/>
            <rdf:type rdf:resource="http://vitro.mannlib.cornell.edu/ns/vitro/0.7#Flag1Value1Thing"/>
          </j.1:excludeEntity>
        </j.3:linkedAuthor>
        <rdfs:label>Authorship for Hall, Martica</rdfs:label>
        <rdf:type rdf:resource="http://vitro.mannlib.cornell.edu/ns/vitro/0.7#DependentResource"/>
        <rdf:type rdf:resource="http://vivoweb.org/ontology/core#Authorship"/>
        <rdf:type rdf:resource="http://vitro.mannlib.cornell.edu/ns/vitro/0.7#Flag1Value1Thing"/>
      </j.3:DependentResource>
    </j.3:informationResourceInAuthorship>
    <j.2:pageStart>183</j.2:pageStart>
    <j.3:freetextKeyword>Quality of Life</j.3:freetextKeyword>
    <j.3:freetextKeyword>Surveys and Questionnaires</j.3:freetextKeyword>
    <j.3:informationResourceInAuthorship>
      <j.3:DependentResource rdf:about="http://vivo.health.unm.edu/individual/n1861873647">
        <j.3:authorRank rdf:datatype="http://www.w3.org/2001/XMLSchema#integer"
        >9</j.3:authorRank>
        <j.3:linkedInformationResource rdf:resource="http://vivo.health.unm.edu/individual/n1840546625"/>
        <j.3:linkedAuthor>
          <j.1:excludeEntity rdf:about="http://vivo.health.unm.edu/individual/n321762621">
            <j.3:middleName>R</j.3:middleName>
            <j.3:authorInAuthorship rdf:resource="http://vivo.health.unm.edu/individual/n1861873647"/>
            <j.4:firstName>Kenneth</j.4:firstName>
            <j.4:lastName>McCurry</j.4:lastName>
            <rdfs:label>McCurry, Kenneth R</rdfs:label>
            <rdf:type rdf:resource="http://xmlns.com/foaf/0.1/Person"/>
            <rdf:type rdf:resource="http://vitro.mannlib.cornell.edu/ns/vitro/0.7#Flag1Value1Thing"/>
          </j.1:excludeEntity>
        </j.3:linkedAuthor>
        <rdfs:label>Authorship for McCurry, Kenneth R</rdfs:label>
        <rdf:type rdf:resource="http://vitro.mannlib.cornell.edu/ns/vitro/0.7#DependentResource"/>
        <rdf:type rdf:resource="http://vivoweb.org/ontology/core#Authorship"/>
        <rdf:type rdf:resource="http://vitro.mannlib.cornell.edu/ns/vitro/0.7#Flag1Value1Thing"/>
      </j.3:DependentResource>
    </j.3:informationResourceInAuthorship>
    <j.3:freetextKeyword>Health Status</j.3:freetextKeyword>
    <j.3:freetextKeyword>Problem Solving</j.3:freetextKeyword>
    <rdf:type rdf:resource="http://vivoweb.org/ontology/core#InformationResource"/>
    <rdf:type rdf:resource="http://purl.org/ontology/bibo/Article"/>
    <j.3:hasPublicationVenue>
      <j.2:Journal rdf:about="http://vivo.health.unm.edu/individual/n397991054">
        <j.3:publicationVenueFor rdf:resource="http://vivo.health.unm.edu/individual/n1840546625"/>
        <j.2:issn>1526-9248</j.2:issn>
        <j.3:Title>Progress in transplantation (Aliso Viejo, Calif.)</j.3:Title>
        <rdfs:label>Progress in transplantation (Aliso Viejo, Calif.)</rdfs:label>
        <rdf:type rdf:resource="http://vitro.mannlib.cornell.edu/ns/vitro/0.7#Flag1Value1Thing"/>
      </j.2:Journal>
    </j.3:hasPublicationVenue>
    <j.3:freetextKeyword>Humans</j.3:freetextKeyword>
    <rdf:type rdf:resource="http://vitro.mannlib.cornell.edu/ns/vitro/0.7#Flag1Value1Thing"/>
    <j.3:freetextKeyword>Regression Analysis</j.3:freetextKeyword>
    <j.3:informationResourceInAuthorship>
      <j.3:DependentResource rdf:about="http://vivo.health.unm.edu/individual/n385127310">
        <j.3:authorRank rdf:datatype="http://www.w3.org/2001/XMLSchema#integer"
        >3</j.3:authorRank>
        <j.3:linkedInformationResource rdf:resource="http://vivo.health.unm.edu/individual/n1840546625"/>
        <j.3:linkedAuthor>
          <j.1:excludeEntity rdf:about="http://vivo.health.unm.edu/individual/n1986217491">
            <j.3:middleName>E</j.3:middleName>
            <j.3:authorInAuthorship rdf:resource="http://vivo.health.unm.edu/individual/n385127310"/>
            <j.4:firstName>Galen</j.4:firstName>
            <j.4:lastName>Switzer</j.4:lastName>
            <rdfs:label>Switzer, Galen E</rdfs:label>
            <rdf:type rdf:resource="http://xmlns.com/foaf/0.1/Person"/>
            <rdf:type rdf:resource="http://vitro.mannlib.cornell.edu/ns/vitro/0.7#Flag1Value1Thing"/>
          </j.1:excludeEntity>
        </j.3:linkedAuthor>
        <rdfs:label>Authorship for Switzer, Galen E</rdfs:label>
        <rdf:type rdf:resource="http://vitro.mannlib.cornell.edu/ns/vitro/0.7#DependentResource"/>
        <rdf:type rdf:resource="http://vivoweb.org/ontology/core#Authorship"/>
        <rdf:type rdf:resource="http://vitro.mannlib.cornell.edu/ns/vitro/0.7#Flag1Value1Thing"/>
      </j.3:DependentResource>
    </j.3:informationResourceInAuthorship>
    <j.2:abstract>Lung transplant candidates face numerous health-related stressors. Although previous work has described the range of coping strategies candidates may use, whether those strategies are related to quality of life in physical functioning, emotional, and social domains has rarely been examined.Adult lung transplant candidates (N = 128) participated in semistructured interviews that included questions regarding global and domain-specific quality of life and a multidimensional assessment of coping with health-related problems. Demographic characteristics, health status, and other psychosocial variables were also assessed, and their effects were examined and controlled in multivariate analyses of the coping-quality-of-life relationship.Respondents were most likely to use active, acceptance, and support-seeking strategies to cope with health problems. Self-blame or avoidance were rarely used. Although used least often, avoidant coping was the most strongly and consistently related to quality of life. With demographic and psychosocial variables controlled, higher avoidant coping remained associated with significantly poorer global quality of life, bodily pain, difficulty with daily work or activities as a function of emotional problems, and depressive symptomatology. Avoidant coping accentuated the association of poor health status and lower quality of life. Among respondents with lower health status, using more avoidant coping was associated with greater difficulty functioning in daily activities as a result of emotional problems. Those with higher health status had less difficulty functioning in daily activities as a result of emotional problems.Transplant team members are encouraged to be aware of and help patients refrain from using avoidant coping strategies.</j.2:abstract>
    <j.3:freetextKeyword>Cross-Sectional Studies</j.3:freetextKeyword>
    <j.3:freetextKeyword>Pennsylvania</j.3:freetextKeyword>
    <j.2:pageEnd>192</j.2:pageEnd>
    <j.3:freetextKeyword>Stress, Psychological</j.3:freetextKeyword>
    <j.3:informationResourceInAuthorship>
      <j.3:DependentResource rdf:about="http://vivo.health.unm.edu/individual/n2140343627">
        <j.3:authorRank rdf:datatype="http://www.w3.org/2001/XMLSchema#integer"
        >1</j.3:authorRank>
        <j.3:linkedInformationResource rdf:resource="http://vivo.health.unm.edu/individual/n1840546625"/>
        <j.3:linkedAuthor>
          <j.1:excludeEntity rdf:about="http://vivo.health.unm.edu/individual/n811242396">
            <j.3:authorInAuthorship rdf:resource="http://vivo.health.unm.edu/individual/n2140343627"/>
            <j.4:firstName>Larissa</j.4:firstName>
            <j.4:lastName>Myaskovsky</j.4:lastName>
            <rdfs:label>Myaskovsky, Larissa</rdfs:label>
            <rdf:type rdf:resource="http://xmlns.com/foaf/0.1/Person"/>
            <rdf:type rdf:resource="http://vitro.mannlib.cornell.edu/ns/vitro/0.7#Flag1Value1Thing"/>
          </j.1:excludeEntity>
        </j.3:linkedAuthor>
        <rdfs:label>Authorship for Myaskovsky, Larissa</rdfs:label>
        <rdf:type rdf:resource="http://vitro.mannlib.cornell.edu/ns/vitro/0.7#DependentResource"/>
        <rdf:type rdf:resource="http://vivoweb.org/ontology/core#Authorship"/>
        <rdf:type rdf:resource="http://vitro.mannlib.cornell.edu/ns/vitro/0.7#Flag1Value1Thing"/>
      </j.3:DependentResource>
    </j.3:informationResourceInAuthorship>
  </j.2:Document>
</rdf:RDF>
